pyeutils/__init__.py
pyeutils/eutils.py
pyeutils/taxonomy.py
pyeutils/core/__init__.py
pyeutils/core/core.py
pyeutils/core/esearch_result.py
pyeutils-0.0.1.dist-info/LICENSE
pyeutils-0.0.1.dist-info/METADATA
pyeutils-0.0.1.dist-info/WHEEL
pyeutils-0.0.1.dist-info/top_level.txt
pyeutils-0.0.1.dist-info/RECORD
