Metadata-Version: 2.1
Name: pyeutils
Version: 0.0.1
Summary: NCBI E-utilities Client
Home-page: https://github.com/Fxe/pyeutils
Author: Filipe Liu
Author-email: fliu@anl.gov
License: MIT
Project-URL: Issues, https://github.com/Fxe/pyeutils/issues
Classifier: Development Status :: 3 - Alpha
Classifier: Topic :: Scientific/Engineering :: Bio-Informatics
Classifier: Intended Audience :: Science/Research
Classifier: Operating System :: OS Independent
Classifier: Programming Language :: Python :: 3.9
Classifier: Programming Language :: Python :: 3.10
Classifier: Programming Language :: Python :: 3.11
Classifier: Natural Language :: English
License-File: LICENSE
Requires-Dist: requests>=2.0.0
